[{"id":"628980862427@s.whatsapp.net","limit":4},{"id":"6287791540625@s.whatsapp.net","limit":10},{"id":"6288260182621@s.whatsapp.net","limit":13},{"id":"6288297519330@s.whatsapp.net","limit":6},{"id":"6287718041407@s.whatsapp.net","limit":0},{"id":"6285714166028@s.whatsapp.net","limit":6},{"id":"12506838746@s.whatsapp.net","limit":4},{"id":"6281213601494@s.whatsapp.net","limit":8},{"id":"6281339259303@s.whatsapp.net","limit":6},{"id":"6283872828972@s.whatsapp.net","limit":13},{"id":"6281282110915@s.whatsapp.net","limit":12},{"id":"6289516101158@s.whatsapp.net","limit":4},{"id":"6281352517378@s.whatsapp.net","limit":5},{"id":"6282150779705@s.whatsapp.net","limit":2},{"id":"6281295293290@s.whatsapp.net","limit":6},{"id":"6285775488833@s.whatsapp.net","limit":5},{"id":"6281946599953@s.whatsapp.net","limit":4},{"id":"6288226819941@s.whatsapp.net","limit":1},{"id":"94756280300@s.whatsapp.net","limit":1},{"id":"6288214214397@s.whatsapp.net","limit":3},{"id":"6282131132088@s.whatsapp.net","limit":7},{"id":"6285836134734@s.whatsapp.net","limit":3},{"id":"628992017617@s.whatsapp.net","limit":1},{"id":"6282171157397@s.whatsapp.net","limit":6},{"id":"6282168522177@s.whatsapp.net","limit":2},{"id":"6289668980568@s.whatsapp.net","limit":1},{"id":"6283143336806@s.whatsapp.net","limit":3},{"id":"17853359473@s.whatsapp.net","limit":17},{"id":"62895353656633@s.whatsapp.net","limit":17},{"id":"6287820315101@s.whatsapp.net","limit":4},{"id":"6285640252680@s.whatsapp.net","limit":1},{"id":"6281318509374@s.whatsapp.net","limit":1},{"id":"6281315312002@s.whatsapp.net","limit":11},{"id":"6281221206726@s.whatsapp.net","limit":14},{"id":"6281314684551@s.whatsapp.net","limit":1},{"id":"6285810893601@s.whatsapp.net","limit":16},{"id":"6289502215830@s.whatsapp.net","limit":4},{"id":"6288215183607@s.whatsapp.net","limit":0},{"id":"6287782040087@s.whatsapp.net","limit":7},{"id":"6287889066920@s.whatsapp.net","limit":15},{"id":"6283892781400@s.whatsapp.net","limit":1},{"id":"6281330311900@s.whatsapp.net","limit":2},{"id":"62895332015892@s.whatsapp.net","limit":1},{"id":"6285715488305@s.whatsapp.net","limit":6},{"id":"6285265817775@s.whatsapp.net","limit":15},{"id":"6281242161010@s.whatsapp.net","limit":20},{"id":"6282187718791@s.whatsapp.net","limit":5},{"id":"6283114855087@s.whatsapp.net","limit":1},{"id":"6282147700981@s.whatsapp.net","limit":1},{"id":"6285816043212@s.whatsapp.net","limit":1},{"id":"6289606860975@s.whatsapp.net","limit":1},{"id":"6282337217335@s.whatsapp.net","limit":4},{"id":"62895704122681@s.whatsapp.net","limit":7},{"id":"62895340588542@s.whatsapp.net","limit":2},{"id":"6282370784874@s.whatsapp.net","limit":1},{"id":"6288221544297@s.whatsapp.net","limit":1},{"id":"62895332550102@s.whatsapp.net","limit":1}]